MANIFEST.in
README
setup.py
OdooRPCLocust/__init__.py
OdooRPCLocust.egg-info/PKG-INFO
OdooRPCLocust.egg-info/SOURCES.txt
OdooRPCLocust.egg-info/dependency_links.txt
OdooRPCLocust.egg-info/requires.txt
OdooRPCLocust.egg-info/top_level.txt