Metadata-Version: 1.1
Name: OdooRPCLocust
Version: 1.0.0
Summary: Easily load test Odoo using Locust and OdooRPC.
Home-page: https://github.com/syleam/OdooRPCLocust
Author: Sylvain GARANCHER
Author-email: sylvain.garancher@syleam.fr
License: BSD
Keywords: odoo locust odoorpc loadtest
Platform: UNKNOWN
Classifier: License :: OSI Approved :: BSD License
Classifier: Programming Language :: Python
